dbdmusic/__init__.py
dbdmusic/__main__.py
dbdmusic-0.0.1.dist-info/METADATA
dbdmusic-0.0.1.dist-info/WHEEL
dbdmusic-0.0.1.dist-info/top_level.txt
dbdmusic-0.0.1.dist-info/RECORD
