Metadata-Version: 1.2
Name: dbdmusic
Version: 0.0.1
Summary: Simplest thing you could use for music in python.
Home-page: UNKNOWN
Author: SilentJungle399
License: UNKNOWN
Platform: UNKNOWN
Classifier: Programming Language :: Python :: 3
Classifier: License :: OSI Approved :: MIT License
Classifier: Operating System :: OS Independent
Requires-Python: >=3.6
